jabir/__init__.py
jabir/jabir.py
jabir-0.0.7.dist-info/LICENSE
jabir-0.0.7.dist-info/METADATA
jabir-0.0.7.dist-info/WHEEL
jabir-0.0.7.dist-info/top_level.txt
jabir-0.0.7.dist-info/RECORD
