Metadata-Version: 2.1
Name: jabir
Version: 0.0.7
Summary: jabir is a package that generates 322 features for any material.
Home-page: https://github.com/Gashmard/jabir
Author: Hassan Gashmard
Author-email: HassanGashmard@gmail.com
License: MIT
Classifier: Programming Language :: Python :: 3
Classifier: License :: OSI Approved :: MIT License
Classifier: Operating System :: OS Independent
Requires-Python: >=3.6
License-File: LICENSE
